qairt/__init__.py
qairt/logging_config.yaml
qairt/qairt_dev_config.yaml
qairt/cli/qairt_vm/qairt_vm.py
qairt/cli/qairt_vm/qairt_vm_context.py
qairt/cli/qairt_vm/qairt_vm_factory.py
qairt/cli/qairt_vm/helpers/qairt_sdk_helper.py
qairt/cli/qairt_vm/utils/config_utils.py
qairt/cli/qairt_vm/utils/confirm_utils.py
qairt/cli/qairt_vm/utils/logging.py
qairt/utils/asset_utils.py
qairt/utils/exceptions.py
qairt/utils/handles.py
qairt/utils/loggers.py
qairt/utils/os_utils.py
qti/aisw/tools/core/utilities/qairt_logging/__init__.py
qti/aisw/tools/core/utilities/qairt_logging/log_areas.py
qti/aisw/tools/core/utilities/qairt_logging/log_config.yaml
qti/aisw/tools/core/utilities/qairt_logging/logging_utility.py
qairt_dev-0.3.0.dist-info/LICENSE.pdf
qairt_dev-0.3.0.dist-info/METADATA
qairt_dev-0.3.0.dist-info/WHEEL
qairt_dev-0.3.0.dist-info/entry_points.txt
qairt_dev-0.3.0.dist-info/top_level.txt
qairt_dev-0.3.0.dist-info/RECORD
