Metadata-Version: 2.2
Name: qairt-dev
Version: 0.3.0
Summary: The Qualcomm AI Runtime Development (QAIRT-DEV) package provides a simple python interface for executing ML models on QAIRT runtimes
Author-email: "Qualcomm Technologies, Inc." <qairt-dev-support@qti.qualcomm.com>
Maintainer-email: qairt-dev-support <qairt-dev-support@qti.qualcomm.com>
License: Proprietary
Classifier: Development Status :: 4 - Beta
Classifier: Intended Audience :: Developers
Classifier: Operating System :: Microsoft :: Windows :: Windows 10
Classifier: Operating System :: POSIX :: Linux
Classifier: Programming Language :: Python :: 3.10
Classifier: Topic :: Scientific/Engineering
Classifier: Topic :: Scientific/Engineering :: Artificial Intelligence
Classifier: Topic :: Software Development
Requires-Python: <3.11,>=3.10
License-File: LICENSE.pdf
Requires-Dist: aenum==3.1.15
Requires-Dist: click<9.0.0,>=8.1.8
Requires-Dist: cryptography<46.0.0,>=45.0.3
Requires-Dist: numpy==1.26.4
Requires-Dist: paramiko==3.5.1
Requires-Dist: pip<26.0,>=25.0
Requires-Dist: protobuf==3.20.2
Requires-Dist: pydantic<2.9.0,>=2.8.2
Requires-Dist: pyyaml<7.0.0,>=6.0.2
Requires-Dist: rich==13.9.4
Requires-Dist: safetensors==0.4.3
Requires-Dist: sentencepiece==0.2.0
Requires-Dist: setuptools<76.0,>=75.0
Requires-Dist: transformers==4.44.0
Requires-Dist: types-paramiko==3.5.0.20250516
Provides-Extra: onnx
Requires-Dist: onnx==1.17.0; extra == "onnx"
Requires-Dist: onnx_ir==0.1.8; extra == "onnx"
Requires-Dist: onnxruntime==1.22.0; extra == "onnx"
Requires-Dist: onnxruntime-genai==0.8.2; extra == "onnx"
Requires-Dist: onnxsim==0.4.36; extra == "onnx"
Requires-Dist: onnx-graphsurgeon==0.5.8; extra == "onnx"
Requires-Dist: onnxscript==0.3.1; extra == "onnx"
Requires-Dist: scipy==1.15.3; extra == "onnx"
Requires-Dist: islpy==2025.2.5; platform_system == "Linux" and extra == "onnx"
Requires-Dist: gguf==0.9.1; extra == "onnx"
Provides-Extra: torch
Requires-Dist: torch==2.4.1; extra == "torch"
Requires-Dist: torchvision==0.19.1; extra == "torch"
